{"data":{"site":{"siteMetadata":{"title":"Spectrum CSS","author":"Garth Braithwaite"}},"markdownRemark":{"id":"86061099-0bb6-525c-8c2a-c2e015364f18","excerpt":"Put the labels below by adding the modifier class to the field itself.","frontmatter":{"title":"Field Group - Labels Below","markup":"<div class=\"spectrum-FieldGroup\">\n  <div class=\"spectrum-Radio spectrum-Radio--labelBelow\">\n    <input type=\"radio\" name=\"rating\" class=\"spectrum-Radio-input\" id=\"radio-2\">\n    <span class=\"spectrum-Radio-button\"></span>\n    <label class=\"spectrum-Radio-label\" for=\"radio-2\">1</label>\n  </div>\n  <div class=\"spectrum-Radio spectrum-Radio--labelBelow\">\n    <input type=\"radio\" name=\"rating\" class=\"spectrum-Radio-input\" id=\"radio-3\">\n    <span class=\"spectrum-Radio-button\"></span>\n    <label class=\"spectrum-Radio-label\" for=\"radio-3\">2</label>\n  </div>\n  <div class=\"spectrum-Radio spectrum-Radio--labelBelow\">\n    <input type=\"radio\" name=\"rating\" class=\"spectrum-Radio-input\" id=\"radio-4\">\n    <span class=\"spectrum-Radio-button\"></span>\n    <label class=\"spectrum-Radio-label\" for=\"radio-4\">3</label>\n  </div>\n</div>\n"}}},"pageContext":{"slug":"/field-group---labels-below/","previous":{"fields":{"slug":"/field-group---vertical/"},"frontmatter":{"title":"Field Group - Vertical"}},"next":{"fields":{"slug":"/field-group/"},"frontmatter":{"title":"Field Group"}}}}