{"data":{"site":{"siteMetadata":{"title":"Gatsby Starter Blog","author":"Kyle Mathews"}},"markdownRemark":{"id":"94d90787-74ee-562e-bb22-7d298285f69c","excerpt":"Simply an action button with a Popover. Note that the   class should be applied to the button when the menu is open. Also note the accessibility roles are…","frontmatter":{"title":"Action Menu","directory":"actionmenu"}}},"pageContext":{"slug":"/action-menu/","previous":{"fields":{"slug":"/alert---closable/"},"frontmatter":{"title":"Alert - Closable"}},"next":{"fields":{"slug":"/action-button---quiet/"},"frontmatter":{"title":"Action Button - Quiet"}}}}