{"data":{"site":{"siteMetadata":{"title":"Gatsby Starter Blog","author":"Kyle Mathews"}},"markdownRemark":{"id":"3e59dc2d-0a1a-5027-88ee-28954a6230c0","excerpt":"The standard Card component with cover photo and footer.","frontmatter":{"title":"Card","directory":"card"}}},"pageContext":{"slug":"/card/","previous":{"fields":{"slug":"/card---gallery/"},"frontmatter":{"title":"Card - Gallery"}},"next":{"fields":{"slug":"/calendar---range-selection/"},"frontmatter":{"title":"Calendar - Range Selection"}}}}