{"data":{"site":{"siteMetadata":{"title":"Gatsby Starter Blog","author":"Kyle Mathews"}},"markdownRemark":{"id":"4afa3446-2466-588f-a7dd-c2b78dc4a8a3","excerpt":"A Spectrum quiet button that’s meant to be placed over a non-standard color. In order to implement this button, you must set the CSS color property of a parent…","html":"<p>A Spectrum quiet button that’s meant to be placed over a non-standard color. In order to implement this button, you must set the CSS color property of a parent element to the same value as the background the button is placed against.</p>","frontmatter":{"title":"Button - Quiet Over Background"}}},"pageContext":{"slug":"/button---quiet-over-background/","previous":{"fields":{"slug":"/button---quiet-primary/"},"frontmatter":{"title":"Button - Quiet Primary"}},"next":{"fields":{"slug":"/button---primary/"},"frontmatter":{"title":"Button - Primary"}}}}